{"forthe": 1, "journalmachine": 7, "learning": 191, "journal": 12, "redirectstatistical": 1, "learningstatistical": 1, "in": 97, "language": 8, "acquisition": 2, "machine": 103, "bar": 1, "is": 77, "a": 132, "field": 12, "of": 147, "computer": 18, "science": 8, "that": 46, "uses": 6, "statistical": 14, "techniques": 5, "to": 120, "give": 1, "systems": 12, "the": 209, "ability": 6, "learn": 12, "ie": 1, "progressively": 1, "improve": 4, "performance": 12, "on": 39, "specific": 1, "task": 4, "with": 29, "data": 44, "without": 3, "being": 5, "explicitly": 3, "programmedrefsupposedly": 1, "paraphraseparaphrased": 1, "from": 29, "cite": 2, "journallastsamuelfirstarthurdate1959titlesome": 1, "studies": 1, "using": 8, "game": 5, "checkersurlhttpsdoiorg101147rd330210journalibm": 1, "research": 8, "and": 141, "developmentvolume3issue3pagesdoi101147rd330210viabr": 1, "confer": 1, "conferenceurlhttpslinkspringercomchapter10100797894009027949titleautomated": 1, "design": 2, "both": 1, "topology": 1, "sizing": 1, "analog": 1, "electrical": 1, "circuits": 1, "genetic": 9, "programmingconferenceartificial": 1, "intelligence": 12, "96lastkozafirstjohn": 1, "rlast2bennettfirst2forrest": 1, "hlast3andrefirst3davidlast4keanefirst4martin": 1, "adate1996publisherspringer": 1, "dordrechtpages151170languageendoi10100797894009027949quoteparaphrasing": 1, "arthur": 3, "samuel": 2, "1959": 3, "question": 3, "how": 3, "can": 20, "computers": 2, "solve": 2, "problems": 5, "programmedref": 1, "name": 1, "was": 6, "coined": 2, "by": 28, "samuelrefcite": 1, "bookurlhttpslinkspringercomchapter101007978146138716914titlecomputer": 1, "games": 1, "ilastsamuelfirstarthur": 1, "ldate1988publisherspringer": 1, "new": 8, "york": 2, "nyisbn9781461387183pages335365languageendoi101007978146138716914ref": 1, "evolved": 1, "study": 5, "pattern": 7, "recognition": 10, "computational": 10, "theory": 10, "artificial": 17, "intelligenceref": 1, "namebritannicahttpwwwbritannicacomebcheckedtopic1116194machinelearning": 1, "tertiaryref": 1, "explores": 1, "construction": 2, "algorithms": 26, "make": 4, "predictions": 5, "datarefcite": 3, "titleglossary": 1, "terms": 5, "author1ron": 1, "kohavi": 2, "author2foster": 1, "provost": 2, "volume30": 1, "pages271274": 1, "year1998": 2, "urlhttpaistanfordeduronnykglossaryhtmlref": 1, "such": 6, "overcome": 1, "following": 2, "strictly": 1, "static": 1, "programprogram": 1, "instructions": 1, "making": 2, "datadriven": 1, "or": 25, "decisionsref": 1, "namebishop": 3, "rp2": 1, "through": 5, "building": 1, "mathematical": 3, "modelmodel": 1, "sample": 1, "inputs": 12, "employed": 2, "range": 1, "computing": 4, "tasks": 7, "where": 7, "designing": 2, "programming": 10, "explicit": 1, "good": 2, "difficult": 3, "infeasible": 1, "example": 8, "applications": 6, "include": 5, "email": 2, "filtering": 2, "detection": 1, "network": 12, "intruders": 1, "malicious": 1, "insiders": 1, "working": 1, "towards": 2, "breachrefcite": 1, "weburlhttpstechcrunchcom20160701exploitingmachinelearningincybersecuritytitleexploiting": 1, "cybersecuritylastdicksonfirstbenwebsitetechcrunchaccessdate20170523ref": 1, "optical": 1, "character": 1, "ocrref": 1, "namewernicksignalprocjuly2010wernick": 1, "yang": 1, "brankov": 1, "yourganov": 1, "strother": 1, "medical": 4, "imaging": 1, "ieee": 3, "signal": 7, "processing": 8, "societyieee": 1, "magazine": 2, "vol": 3, "27": 1, "no": 4, "4": 1, "july": 1, "2010": 2, "pp": 3, "2538ref": 1, "rank": 1, "vision": 4, "closely": 2, "related": 5, "often": 10, "overlaps": 1, "statistics": 8, "which": 12, "also": 15, "focuses": 4, "predictionmaking": 1, "use": 6, "it": 20, "has": 13, "strong": 1, "ties": 2, "optimization": 3, "delivers": 1, "methods": 14, "application": 2, "domains": 1, "sometimes": 3, "conflated": 1, "miningrefcite": 1, "conference": 7, "lastmannila": 1, "firstheikki": 1, "titledata": 1, "mining": 11, "databases": 3, "conferenceintl": 1, "conf": 1, "scientific": 2, "database": 3, "management": 1, "publisherieee": 2, "society": 2, "year1996ref": 1, "latter": 1, "subfield": 1, "more": 8, "exploratory": 1, "analysis": 11, "known": 8, "as": 32, "unsupervised": 10, "learningref": 2, "namebishopmachine": 1, "be": 25, "viewed": 1, "two": 11, "facets": 1, "same": 5, "fieldrefrpviirefcite": 1, "lastfriedman": 1, "firstjerome": 1, "h": 5, "authorlink": 1, "jerome": 2, "friedmantitledata": 1, "whats": 1, "connection": 1, "journalcomputing": 1, "volume29": 1, "issue1": 1, "pages39ref": 1, "unsupervisedrefcite": 1, "weburlhttpwwwdarkreadingcomthreatintelligence3flavorsofmachinelearningwhowhatandwhereadid1324278titledark": 1, "readinglastfirstdatewebsitepublisheraccessdateref": 1, "used": 15, "establish": 1, "baseline": 1, "behavioral": 1, "profiles": 1, "for": 39, "various": 5, "entitiesrefcite": 1, "weburlhttpaibusinessorglightcybersjasonmatlofexplainshowmagnadetectshackersbeforetheyattacktitleai": 1, "businesslastfirstdatewebsitepublisheraccessdateref": 1, "then": 7, "find": 5, "meaningful": 1, "anomalies": 1, "within": 3, "analytics": 4, "method": 10, "devise": 1, "complex": 4, "models": 9, "lend": 1, "themselves": 1, "prediction": 3, "commercial": 1, "this": 14, "predictive": 3, "these": 7, "analytical": 1, "allow": 2, "researchers": 4, "sciencedata": 1, "scientists": 1, "engineers": 1, "analysts": 1, "produce": 3, "reliable": 1, "repeatable": 1, "decisions": 1, "results": 4, "uncover": 1, "hidden": 3, "insights": 1, "historical": 1, "relationships": 4, "trends": 1, "weburlhttpwwwsascomititinsightsanalyticsmachinelearninghtmltitlemachine": 1, "what": 3, "why": 1, "matterswebsitewwwsascomaccessdate20160329ref": 1, "effective": 2, "because": 4, "finding": 2, "patterns": 4, "hard": 1, "not": 7, "enough": 2, "training": 19, "are": 33, "available": 4, "result": 1, "machinelearning": 1, "programs": 3, "fail": 3, "deliverrefcite": 1, "newsurlhttpswwwbloombergcomnewsarticles20161110whymachinelearningmodelsoftenfailtolearnquicktakeqatitlewhy": 1, "quicktake": 1, "qadate20161110workbloombergcomaccessdate20170410refrefcite": 1, "newsurlhttpswwwtechnologyreviewcoms603944microsoftaiisntyetadaptableenoughtohelpbusinessestitlemicrosoft": 1, "says": 1, "its": 12, "racist": 4, "chatbot": 1, "illustrates": 1, "ai": 11, "isnt": 1, "adaptable": 1, "help": 1, "most": 1, "businesseslastsimonitefirsttomworkmit": 1, "technology": 1, "reviewaccessdate20170410languageenref": 1, "overview": 1, "tom": 1, "m": 6, "mitchell": 1, "provided": 2, "widely": 1, "quoted": 1, "formal": 1, "definition": 3, "studied": 2, "program": 4, "said": 1, "experience": 4, "e": 4, "respect": 3, "some": 12, "class": 4, "t": 3, "measure": 1, "p": 3, "if": 6, "at": 6, "measured": 1, "improves": 1, "erefcite": 1, "book": 4, "authormitchell": 1, "titlemachine": 2, "publishermcgraw": 1, "hill": 1, "isbn": 3, "0070428077": 1, "pages2": 1, "year1997ref": 1, "concerned": 3, "offers": 1, "fundamentally": 1, "operational": 1, "definitionoperational": 1, "rather": 2, "than": 5, "defining": 2, "cognitive": 1, "follows": 1, "alan": 1, "turings": 2, "proposal": 2, "his": 1, "paper": 2, "machinery": 2, "machines": 7, "think": 1, "replaced": 1, "do": 4, "we": 2, "thinking": 3, "entities": 1, "dorefcitation": 1, "chapterurlhttpeprintsecssotonacuk12954": 1, "author": 2, "stevan": 1, "harnad": 1, "year2008": 1, "chapterthe": 1, "annotation": 1, "turing": 2, "1950": 1, "editor1lastepstein": 1, "editor1firstrobert": 1, "editor2lastpeters": 1, "editor2firstgrace": 1, "titlethe": 1, "test": 6, "sourcebook": 1, "philosophical": 1, "methodological": 2, "issues": 1, "quest": 2, "location": 1, "publisherkluwer": 1, "ref": 5, "characteristics": 1, "could": 2, "possessed": 1, "implications": 1, "constructing": 1, "one": 8, "exposed": 1, "anchoralgorithm": 1, "types": 1, "typically": 4, "classified": 1, "into": 9, "broad": 1, "categories": 3, "depending": 1, "whether": 2, "there": 2, "feedback": 3, "system": 6, "supervised": 8, "presented": 3, "their": 9, "desired": 2, "outputs": 5, "given": 10, "teacher": 1, "goal": 4, "general": 5, "rule": 6, "map": 1, "mathematicsmaps": 1, "special": 2, "cases": 2, "input": 5, "only": 5, "partially": 1, "restricted": 1, "semisupervised": 1, "an": 28, "incomplete": 1, "set": 18, "many": 4, "target": 2, "missing": 1, "active": 2, "learningactive": 1, "obtain": 1, "labels": 4, "limited": 1, "instances": 5, "based": 4, "budget": 1, "optimize": 1, "choice": 1, "objects": 3, "acquire": 2, "when": 3, "interactively": 1, "user": 3, "labeling": 1, "reinforcement": 6, "form": 1, "rewards": 1, "punishments": 1, "actions": 4, "dynamic": 1, "environment": 2, "autonomous": 2, "cardriving": 1, "vehicle": 1, "playing": 2, "against": 3, "opponentref": 1, "rp3": 2, "algorithm": 12, "leaving": 1, "own": 3, "structure": 3, "itself": 1, "discovering": 3, "means": 3, "end": 5, "feature": 1, "filesvm": 1, "max": 1, "sep": 1, "hyperplane": 1, "marginpngthumba": 1, "support": 3, "vector": 4, "classifier": 6, "divides": 1, "space": 5, "regions": 1, "separated": 1, "linear": 3, "classifierlinear": 1, "boundary": 1, "here": 1, "learned": 6, "distinguish": 1, "black": 1, "white": 1, "circles": 1, "another": 1, "categorization": 1, "arises": 2, "considers": 2, "output": 1, "machinelearned": 1, "systemref": 1, "classificationclassification": 2, "divided": 2, "classes": 5, "learner": 5, "must": 1, "model": 22, "assigns": 1, "unseen": 4, "multilabel": 1, "classification": 9, "tackled": 1, "way": 4, "spam": 3, "other": 9, "messages": 1, "regression": 2, "analysisregression": 2, "problem": 8, "continuous": 1, "discrete": 1, "cluster": 5, "analysisclustering": 1, "groups": 2, "unlike": 1, "beforehand": 1, "density": 2, "estimation": 3, "finds": 1, "probability": 5, "distributiondistribution": 1, "dimensionality": 1, "reduction": 1, "simplifies": 1, "mapping": 1, "them": 2, "lowerdimensional": 1, "topic": 1, "modeling": 4, "list": 4, "natural": 5, "languagehuman": 1, "documents": 2, "tasked": 1, "out": 3, "cover": 1, "similar": 5, "topics": 1, "among": 1, "meta": 1, "sciencelearning": 1, "learns": 3, "inductive": 7, "bias": 3, "previous": 2, "developmental": 1, "roboticsdevelopmental": 1, "elaborated": 1, "robot": 2, "generates": 1, "sequences": 2, "called": 3, "curriculum": 1, "situations": 1, "cumulatively": 1, "repertoires": 1, "novel": 1, "skills": 1, "selfexploration": 1, "social": 1, "interaction": 1, "human": 3, "teachers": 1, "guidance": 1, "mechanisms": 1, "maturation": 1, "motor": 1, "synergies": 1, "imitation": 1, "history": 2, "fields": 3, "see": 2, "alsotimeline": 1, "american": 1, "pioneer": 1, "gamingcomputer": 1, "gaming": 1, "term": 3, "while": 8, "ibmrefr": 1, "f": 1, "glossary": 1, "30": 1, "23": 2, "271274": 1, "1998ref": 1, "endeavour": 1, "grew": 1, "already": 2, "early": 1, "days": 1, "academic": 2, "discipline": 1, "were": 6, "interested": 1, "having": 2, "they": 6, "attempted": 1, "approach": 7, "symbolic": 2, "well": 2, "termed": 1, "neural": 14, "networks": 11, "mostly": 2, "perceptrons": 1, "adalineother": 1, "later": 1, "found": 2, "reinventions": 1, "generalized": 1, "statisticsrefcite": 1, "last1sarlefirst1warrentitleneural": 1, "modelsjournalciteseerx101127699ref": 1, "theoryprobabilistic": 1, "reasoning": 3, "especially": 1, "automated": 5, "diagnosisref": 1, "nameaimacite": 1, "aimaedition2refrp488": 1, "however": 2, "increasing": 2, "emphasis": 1, "gofailogical": 1, "knowledgebased": 1, "caused": 1, "rift": 1, "between": 11, "probabilistic": 3, "plagued": 1, "theoretical": 3, "practical": 3, "representationref": 1, "nameaima": 3, "rp488": 1, "1980": 1, "expert": 1, "had": 5, "come": 2, "dominate": 1, "favorref": 1, "namechangingcite": 1, "last1": 1, "langley": 1, "first1": 1, "pat": 1, "title": 2, "changing": 1, "doi": 1, "101007s109940115242y": 1, "volume": 1, "82": 1, "issue": 1, "3": 1, "pages": 2, "275279": 1, "year": 2, "2011": 2, "pmid": 1, "pmc": 1, "work": 2, "symbolicknowledgebased": 1, "did": 1, "continue": 1, "leading": 2, "logic": 7, "but": 6, "line": 2, "now": 2, "outside": 2, "proper": 1, "information": 9, "retrievalref": 1, "rp708710": 1, "755": 1, "been": 8, "abandoned": 1, "around": 1, "time": 8, "too": 2, "continued": 1, "aics": 1, "connectionism": 1, "disciplines": 1, "including": 2, "john": 1, "hopfieldhopfield": 1, "david": 3, "rumelhartrumelhart": 1, "geoff": 1, "hintonhinton": 1, "main": 17, "success": 1, "came": 1, "mid1980s": 1, "reinvention": 1, "backpropagationref": 1, "rp25": 1, "reorganized": 1, "separate": 3, "started": 1, "flourish": 1, "1990s": 1, "changed": 2, "achieving": 1, "tackling": 1, "solvable": 1, "nature": 1, "shifted": 1, "focus": 1, "away": 1, "approaches": 3, "inherited": 1, "toward": 1, "borrowed": 1, "theoryref": 1, "namechanging": 1, "benefited": 1, "availability": 1, "digitized": 1, "distribute": 1, "via": 2, "internet": 3, "employ": 1, "overlap": 1, "significantly": 1, "properties": 2, "discovery": 5, "observationdiscovery": 1, "previously": 5, "unknown": 5, "step": 3, "knowledge": 10, "different": 5, "goals": 1, "hand": 1, "employs": 1, "preprocessing": 2, "accuracy": 5, "much": 1, "confusion": 1, "communities": 1, "have": 6, "conferences": 2, "journals": 2, "ecml": 1, "pkdd": 1, "major": 1, "exception": 1, "comes": 1, "basic": 2, "assumptions": 2, "usually": 4, "evaluated": 3, "reproduce": 1, "kdd": 2, "key": 2, "uninformed": 1, "will": 4, "easily": 1, "outperformed": 1, "typical": 1, "cannot": 2, "due": 1, "unavailability": 1, "intimate": 1, "formulated": 1, "minimization": 1, "loss": 4, "function": 6, "examples": 9, "functions": 3, "express": 2, "discrepancy": 1, "trained": 4, "actual": 2, "wants": 1, "assign": 1, "label": 1, "correctly": 1, "predict": 4, "preassigned": 1, "difference": 1, "generalization": 5, "minimize": 1, "minimizing": 1, "samplesrefcite": 1, "encyclopedia": 1, "last1le": 1, "roux": 1, "first1nicolas": 1, "first2yoshua": 1, "last2bengio": 1, "first3andrew": 1, "last3fitzgibbon": 1, "titleimproving": 1, "first": 2, "secondorder": 1, "uncertainty": 1, "encyclopediaoptimization": 1, "year2012": 1, "page404": 1, "editorlast1sra": 1, "editorfirst1suvrit": 1, "editorfirst2sebastian": 1, "editorlast2nowozin": 1, "editorfirst3stephen": 1, "j": 4, "editorlast3wright": 1, "publishermit": 1, "pressref": 1, "relation": 1, "according": 2, "michael": 2, "i": 2, "jordan": 3, "ideas": 1, "principles": 1, "tools": 3, "long": 1, "prehistory": 1, "statisticsref": 1, "namemi": 2, "amacite": 1, "weburlhttpswwwredditcomrmachinelearningcomments2fxi6vamamichaelijordanckelmttcontext3": 1, "titlestatistics": 1, "learningpublisherredditdate20140910accessdate20141001languageauthor": 1, "jordanref": 1, "he": 1, "suggested": 1, "placeholder": 1, "call": 2, "overall": 2, "fieldref": 1, "ama": 1, "leo": 1, "breiman": 1, "distinguished": 1, "modelling": 1, "paradigms": 1, "algorithmic": 4, "modelrefcite": 1, "weburlhttpprojecteuclidorgdownloadpdf1euclidss1009213726titlebreiman": 1, "cultures": 1, "comments": 1, "rejoinder": 1, "authorauthorcornell": 1, "university": 3, "librarypublisheraccessdate8": 1, "august": 2, "2015ref": 2, "wherein": 1, "less": 3, "like": 2, "random": 2, "forest": 1, "statisticians": 1, "adopted": 1, "combined": 1, "nameislrcite": 1, "author1gareth": 1, "james": 2, "author2daniela": 1, "witten": 2, "author3trevor": 1, "hastie": 2, "author4robert": 1, "tibshirani": 2, "titlean": 1, "introduction": 4, "publisherspringer": 2, "year2013": 1, "urlhttpwwwbcfuscedugarethisl": 1, "pageviiref": 1, "anchorgeneralization": 1, "articlecomputational": 1, "core": 1, "objective": 1, "generalize": 1, "experienceref": 1, "namebishop2006citationfirst": 1, "c": 5, "last": 2, "bishop": 3, "authorlinkchristopher": 1, "year2006": 1, "titlepattern": 1, "isbn0387310738refrefcite": 1, "mehryar": 1, "afshin": 1, "ameet": 1, "2012ref": 2, "context": 2, "perform": 2, "accurately": 1, "examplestasks": 1, "after": 2, "experienced": 1, "generally": 2, "distribution": 4, "considered": 3, "representative": 1, "occurrences": 1, "build": 1, "about": 4, "enables": 1, "sufficiently": 1, "accurate": 1, "branch": 1, "sets": 1, "finite": 1, "future": 1, "uncertain": 1, "does": 1, "yield": 1, "guarantees": 1, "instead": 1, "bounds": 2, "quite": 1, "common": 2, "biasvariance": 1, "decomposition": 1, "quantify": 1, "errors": 1, "residualserror": 1, "best": 3, "complexity": 5, "hypothesis": 3, "should": 1, "match": 1, "underlying": 2, "underfit": 1, "increased": 1, "response": 1, "error": 1, "decreases": 1, "subject": 1, "overfitting": 1, "poorerref": 1, "namealpaydincite": 1, "bookauthoralpaydin": 1, "ethemtitleintroduction": 1, "learningurlhttpsmitpressmitedubooksintroductionmachinelearning": 1, "year2010": 1, "publisherthe": 1, "mit": 2, "press": 4, "placelondonisbn": 1, "9780262012430": 1, "accessdate4": 1, "february": 1, "2017": 2, "addition": 3, "theorists": 1, "feasibility": 1, "computation": 5, "feasible": 1, "done": 1, "complexitypolynomial": 1, "timepolynomial": 1, "kinds": 1, "positive": 5, "show": 2, "certain": 2, "polynomial": 2, "negative": 5, "articlelist": 1, "decision": 3, "tree": 4, "articledecision": 1, "modellingpredictive": 1, "maps": 2, "observations": 4, "item": 1, "conclusions": 1, "items": 1, "value": 1, "association": 3, "articleassociation": 1, "interesting": 1, "relations": 1, "variables": 3, "large": 1, "articleartificial": 1, "ann": 1, "nn": 1, "vaguely": 1, "inspired": 1, "biological": 1, "computations": 1, "structured": 1, "interconnected": 1, "group": 1, "neurons": 1, "connectionismconnectionist": 1, "modern": 2, "nonlinear": 1, "recognitionfind": 1, "capture": 1, "joint": 3, "observed": 2, "deep": 9, "articledeep": 1, "falling": 1, "hardware": 1, "prices": 1, "development": 2, "gpus": 1, "personal": 1, "few": 1, "years": 1, "contributed": 1, "concept": 1, "consists": 1, "multiple": 2, "layers": 1, "tries": 1, "brain": 1, "processes": 1, "light": 1, "sound": 1, "hearing": 1, "successful": 2, "speech": 3, "recognitionrefhonglak": 1, "lee": 1, "roger": 1, "grosse": 1, "rajesh": 1, "ranganath": 1, "andrew": 2, "y": 1, "ng": 3, "httpciteseerxistpsueduviewdocdownloaddoi1011149802reprep1typepdf": 1, "convolutional": 1, "belief": 3, "scalable": 1, "hierarchical": 1, "representations": 6, "proceedings": 1, "26th": 1, "annual": 1, "international": 4, "2009ref": 1, "articleinductive": 1, "ilp": 2, "uniform": 1, "representation": 9, "background": 2, "hypotheses": 2, "encoding": 1, "represented": 4, "logical": 1, "facts": 1, "derive": 1, "hypothesized": 1, "entailmententails": 1, "all": 1, "any": 3, "kind": 1, "languages": 1, "representing": 1, "functional": 1, "programmingfunctional": 1, "articlesupport": 1, "svms": 1, "each": 3, "marked": 1, "belonging": 1, "svm": 1, "builds": 1, "predicts": 1, "falls": 1, "category": 1, "clustering": 3, "articlecluster": 1, "assignment": 1, "subsets": 2, "clusters": 3, "so": 4, "predesignated": 1, "criterion": 1, "criteria": 1, "drawn": 1, "dissimilar": 1, "defined": 2, "similarity": 6, "metric": 3, "internal": 1, "compactness": 1, "members": 1, "separation": 1, "estimated": 1, "graph": 2, "connectivity": 1, "technique": 1, "statisticsstatistical": 1, "bayesian": 3, "articlebayesian": 1, "directed": 2, "acyclic": 2, "graphical": 3, "modelprobabilistic": 1, "represents": 2, "conditional": 1, "independenceconditional": 1, "independencies": 1, "dag": 1, "represent": 3, "diseases": 2, "symptoms": 2, "compute": 1, "probabilities": 1, "presence": 1, "efficient": 1, "exist": 1, "inference": 4, "articlereinforcement": 1, "agent": 2, "ought": 2, "take": 2, "maximize": 1, "notion": 1, "longterm": 1, "reward": 1, "attempt": 4, "policy": 1, "states": 2, "world": 1, "those": 1, "differs": 1, "correct": 1, "inputoutput": 1, "pairs": 3, "never": 2, "nor": 1, "suboptimal": 1, "corrected": 1, "articlerepresentation": 1, "several": 2, "aim": 2, "better": 2, "during": 1, "classical": 1, "principal": 1, "components": 1, "preserve": 1, "transform": 1, "makes": 1, "useful": 1, "before": 1, "performing": 2, "allowing": 1, "reconstruction": 1, "coming": 1, "generating": 2, "necessarily": 2, "faithful": 1, "configurations": 1, "implausible": 1, "under": 4, "manifold": 1, "constraint": 2, "lowdimensional": 2, "sparse": 12, "coding": 1, "zeros": 1, "multilinear": 2, "subspace": 2, "directly": 1, "tensor": 2, "multidimensional": 1, "reshaping": 1, "highdimensional": 1, "vectorsrefcite": 1, "first1haiping": 1, "last1lu": 1, "first2kn": 1, "last2plataniotis": 1, "first3an": 1, "last3venetsanopoulos": 1, "urlhttpwwwdsputorontocahaipingpublicationsurveymslpr2011pdf": 1, "titlea": 1, "survey": 2, "journalpattern": 1, "volume44": 1, "number7": 1, "pages15401551": 1, "year2011": 2, "doi101016jpatcog201101004ref": 1, "discover": 1, "levels": 2, "hierarchy": 1, "features": 3, "higherlevel": 1, "abstract": 1, "lowerlevel": 1, "argued": 1, "intelligent": 1, "disentangles": 1, "factors": 1, "variation": 1, "explain": 1, "architectures": 1, "yoshua": 1, "bengio": 1, "publisher": 1, "publishers": 1, "inc": 1, "2009": 2, "9781601982940": 1, "13": 2, "url": 1, "httpsbooksgooglecombooksidcq5ewg7fnimcpgpa3": 1, "articlesimilarity": 1, "needs": 1, "distance": 1, "recommendation": 4, "dictionary": 11, "articlesparse": 1, "datum": 4, "combination": 1, "basis": 2, "coefficients": 1, "assumed": 2, "let": 1, "x": 2, "ddimensional": 1, "d": 6, "n": 3, "matrix": 1, "column": 1, "r": 3, "coefficient": 1, "mathematically": 1, "solving": 1, "mathx": 1, "approx": 1, "rmath": 1, "speaking": 1, "larger": 1, "freedom": 1, "along": 1, "strongly": 1, "nphard": 1, "approximatelyrefa": 1, "tillmann": 1, "httpsdxdoiorg101109lsp20142345761": 1, "intractability": 1, "exact": 1, "approximate": 1, "letters": 1, "221": 1, "2015": 2, "4549ref": 1, "popular": 2, "heuristic": 2, "ksvd": 2, "applied": 4, "contexts": 1, "determine": 1, "belongs": 1, "suppose": 1, "built": 2, "associated": 2, "sparsely": 2, "corresponding": 1, "image": 3, "denoising": 1, "idea": 1, "clean": 1, "patch": 1, "noise": 1, "cannotrefaharon": 1, "elad": 1, "bruckstein": 1, "2006": 2, "overcomplete": 1, "dictionaries": 1, "transactions": 2, "54": 1, "11": 1, "43114322ref": 1, "articlegenetic": 1, "ga": 1, "search": 3, "algorithmsearch": 1, "scienceheuristic": 1, "mimics": 1, "process": 1, "selection": 1, "mutation": 1, "algorithmmutation": 1, "crossover": 1, "algorithmcrossover": 1, "generate": 1, "chromosome": 1, "algorithmgenotype": 1, "hope": 1, "solutions": 1, "1980s": 1, "1990srefcite": 1, "last1goldberg": 1, "first1david": 1, "first2john": 1, "last2holland": 1, "titlegenetic": 1, "volume3": 1, "issue2": 1, "year1988": 1, "pages9599": 1, "doi101007bf00113892refrefcite": 1, "first1d": 1, "last1michie": 1, "first2d": 1, "last2spiegelhalter": 1, "first3c": 1, "last3taylor": 1, "year1994": 1, "publisherellis": 1, "horwoodref": 1, "conversely": 1, "evolutionary": 1, "algorithmsrefcite": 1, "last1zhang": 1, "first1jun": 1, "last2zhan": 1, "first2zhihui": 1, "last3lin": 1, "first3ying": 1, "last4chen": 1, "first4ni": 1, "last5gong": 1, "first5yuejiao": 1, "last6zhong": 1, "first6jinghui": 1, "last7chung": 1, "first7henry": 1, "sh": 1, "last8li": 1, "first8yun": 1, "last9shi": 1, "first9yuhui": 1, "titleevolutionary": 1, "meets": 1, "journalcomputational": 1, "volume6": 1, "issue4": 1, "pages6875": 1, "urlhttpieeexploreieeeorgiel510207605235706052374pdfarnumber6052374": 1, "doi101109mci2011942584ref": 1, "rulebased": 6, "identifies": 1, "evolves": 1, "rules": 4, "store": 2, "manipulate": 1, "apply": 2, "characteristic": 3, "identification": 1, "utilization": 1, "relational": 1, "collectively": 2, "captured": 1, "contrast": 1, "learners": 1, "commonly": 2, "identify": 2, "singular": 1, "universally": 1, "instance": 2, "order": 2, "predictionrefcite": 1, "journallastbasselfirstgeorge": 1, "wlast2glaabfirst2enricolast3marquezfirst3juliettalast4holdsworthfirst4michael": 1, "jlast5bacarditfirst5jaumedate20110901titlefunctional": 1, "arabidopsis": 1, "largescale": 1, "setsurlhttpwwwplantcellorgcontent2393101journalthe": 1, "plant": 1, "celllanguageenvolume23issue9pages31013116doi101105tpc111088153issn1532298xpmc3203449pmid21896882ref": 1, "immune": 1, "articlelearning": 1, "lcs": 1, "family": 1, "combine": 1, "component": 2, "eg": 1, "either": 1, "seek": 1, "contextdependent": 1, "piecewise": 1, "manner": 1, "predictionsrefcite": 1, "journallasturbanowiczfirstryan": 1, "jlast2moorefirst2jason": 1, "hdate20090922titlelearning": 1, "complete": 1, "review": 1, "roadmapurlhttpwwwhindawicomarchive2009736398journaljournal": 1, "evolution": 1, "applicationslanguageenvolume2009pages125doi1011552009736398issn16876229ref": 1, "div": 7, "col": 5, "theorem": 2, "provingrefbridge": 1, "sean": 1, "b": 1, "holden": 1, "lawrence": 1, "paulson": 1, "httpswwwclcamacuklp15papersreportsbridgemlpdf": 1, "firstorder": 1, "proving": 1, "532": 1, "2014": 3, "141172refrefloos": 1, "sarah": 1, "et": 1, "al": 1, "httpsarxivorgpdf170106972": 1, "guided": 1, "proof": 1, "arxiv": 2, "preprint": 1, "arxiv170106972": 1, "2017ref": 2, "adaptive": 1, "websitescitation": 1, "neededdateaugust": 1, "affective": 1, "bioinformatics": 2, "brainmachine": 1, "interfaces": 1, "cheminformatics": 1, "classifying": 1, "dna": 1, "anatomy": 1, "networksimulationcomputer": 1, "object": 1, "detecting": 1, "creditcard": 1, "fraud": 2, "playingreffinnsson": 1, "hilmar": 1, "yngvi": 1, "bj\u00f6rnsson": 1, "httpsvvvvwaaaiorgpapersaaai2008aaai08041pdf": 1, "simulationbased": 1, "aaai": 1, "8": 1, "2008ref": 1, "retrieval": 1, "detectionref": 1, "namealpaydin": 1, "linguistics": 1, "marketing": 1, "control": 1, "perception": 1, "diagnosis": 2, "intelligencemedical": 1, "economics": 1, "insurance": 1, "understandingrefsarikaya": 1, "ruhi": 1, "geoffrey": 1, "hinton": 1, "anoop": 1, "deoras": 1, "httpwwwcsutorontocahintonabspsruhijournalpdf": 1, "understanding": 1, "ieeeacm": 1, "audio": 1, "taslp": 1, "224": 1, "778784ref": 1, "optimizationoptimization": 1, "metaheuristic": 1, "online": 4, "advertising": 1, "recommender": 1, "locomotion": 1, "engines": 1, "sentiment": 1, "opinion": 1, "sequence": 1, "software": 8, "engineering": 1, "recognitionspeech": 1, "handwriting": 1, "financial": 2, "market": 1, "structural": 1, "health": 1, "monitoring": 1, "syntactic": 1, "seriestime": 1, "series": 1, "forecasting": 1, "behavior": 1, "translationrefcite": 1, "weburlhttpenglishyonhapnewscokrnews201701100200000000aen20170110009700320htmldid2106mtitleaibased": 1, "translation": 1, "soon": 1, "reach": 1, "industry": 1, "officialspublisheryonhap": 1, "news": 1, "agencyaccessdate4": 1, "mar": 1, "2017refdiv": 1, "movie": 2, "company": 1, "netflix": 5, "held": 1, "prize": 3, "competition": 1, "preferences": 1, "existing": 1, "cinematch": 1, "least": 1, "10": 2, "team": 1, "made": 1, "up": 1, "att": 1, "labsresearch": 1, "collaboration": 1, "teams": 1, "big": 2, "chaos": 1, "pragmatic": 1, "ensemble": 1, "averagingensemble": 1, "win": 1, "grand": 1, "1": 1, "millionrefhttpwww2researchattcomvolinskynetflix": 1, "belkor": 1, "home": 1, "page": 1, "researchattcomref": 1, "shortly": 1, "awarded": 1, "realized": 1, "viewers": 1, "ratings": 1, "indicators": 1, "viewing": 1, "everything": 1, "engine": 1, "accordinglyrefcite": 1, "weburlhttptechblognetflixcom201204netflixrecommendationsbeyond5starshtmltitlethe": 1, "tech": 1, "blog": 1, "recommendations": 1, "beyond": 1, "5": 1, "stars": 1, "part": 3, "1publisheraccessdate8": 1, "wall": 1, "street": 1, "wrote": 1, "firm": 2, "rebellion": 1, "crisis": 1, "refhttpswwwwsjcomarticlessb10001424052748703834604575365310813948080ref": 1, "2012": 1, "cofounder": 1, "sun": 1, "microsystems": 1, "vinod": 1, "khosla": 1, "predicted": 1, "80": 1, "doctors": 2, "jobs": 1, "would": 1, "lost": 1, "next": 1, "decades": 1, "diagnostic": 2, "softwarerefcite": 1, "weburlhttpstechcrunchcom20120110doctorsoralgorithmsauthorvonod": 1, "khoslapublishertech": 1, "crunchtitledo": 1, "need": 1, "algorithmsdatejanuary": 1, "reported": 1, "art": 4, "fine": 2, "paintings": 2, "may": 3, "revealed": 1, "unrecognized": 1, "influences": 1, "artistsrefhttpsmediumcomthephysicsarxivblogwhenamachinelearningalgorithmstudiedfineartpaintingsitsawthingsarthistorianshadneverb8e4e7bf7d3e": 1, "saw": 1, "things": 1, "historians": 1, "noticed": 1, "physics": 1, "blogref": 1, "assessments": 1, "validated": 1, "setholdout": 1, "splits": 2, "conventionally": 1, "designation": 1, "evaluates": 1, "comparison": 1, "nfoldcrossvalidation": 1, "statisticscrossvalidation": 1, "randomly": 1, "k": 1, "k1": 1, "train": 1, "kth": 1, "holdout": 1, "crossvalidation": 2, "bootstrap": 2, "samples": 1, "replacement": 1, "dataset": 1, "assess": 1, "accuracyrefcite": 1, "journallast1kohavifirst1rontitlea": 1, "selectionjournalinternational": 1, "intelligencedate1995urlhttpwebcsiastateedujtiancs573paperskohaviijcai95pdfref": 1, "investigators": 2, "frequently": 1, "report": 3, "sensitivity": 1, "specificity": 1, "meaning": 1, "true": 2, "rate": 4, "tpr": 1, "tnr": 1, "respectively": 1, "similarly": 1, "false": 2, "ratefalse": 2, "fpr": 1, "fnr": 1, "rates": 2, "ratios": 1, "reveal": 1, "numerators": 2, "denominators": 2, "total": 1, "operating": 2, "toc": 3, "shows": 1, "mentioned": 1, "thus": 3, "provides": 1, "receiver": 1, "roc": 1, "rocs": 1, "area": 1, "curve": 1, "auc": 1, "ethics": 3, "poses": 1, "host": 1, "ethicsethical": 1, "questions": 1, "datasets": 2, "collected": 1, "biases": 3, "exhibit": 1, "upon": 1, "digitizing": 1, "cultural": 1, "prejudicesrefcite": 1, "weburlhttpwwwnickbostromcomethicsartificialintelligencepdftitlethe": 1, "intelligencelastbostromfirstnickdate2011websitepublisheraccessdate11": 1, "april": 1, "2016": 1, "job": 2, "hiring": 2, "policies": 1, "lead": 1, "duplicating": 1, "scoring": 1, "applicants": 1, "applicantsref": 1, "nameedionwe": 1, "outlinecite": 2, "weblast1edionwefirst1tolulopetitlethe": 1, "fight": 1, "algorithmsurlhttpstheoutlinecompost1571thefightagainstracistalgorithmswebsitethe": 1, "outlineaccessdate17": 2, "november": 2, "2017refref": 1, "namejeffries": 1, "weblast1jeffriesfirst1adriannetitlemachine": 1, "racisturlhttpstheoutlinecompost1439machinelearningisracistbecausetheinternetisracistwebsitethe": 1, "responsible": 1, "collectioncollection": 1, "documentation": 1, "critical": 1, "contains": 1, "text": 1, "corpuscorpora": 1, "biasrefhttpsfreedomtotinkercom20160824languagenecessarilycontainshumanbiasesandsowillmachinestrainedonlanguagecorporaref": 1, "suites": 1, "containing": 1, "variety": 1, "free": 5, "opensource": 3, "col15em": 3, "microsoftcognitivetoolkitcntk": 1, "deeplearning4j": 1, "dlib": 1, "elki": 1, "gnu": 2, "octave": 2, "h2o": 1, "toolh2o": 1, "apache": 1, "mahoutmahout": 1, "mallet": 1, "projectmallet": 1, "multi": 1, "expression": 1, "programmingmepx": 1, "mlpy": 1, "mlpack": 1, "librarymlpack": 1, "moa": 1, "massive": 1, "mxnet": 1, "nd4j": 1, "softwarend4j": 1, "nd": 1, "arrays": 1, "java": 1, "numentathe": 1, "nupic": 1, "open": 1, "source": 1, "projectnupic": 1, "openaiopenai": 1, "gymopenai": 1, "gym": 1, "openaiuniverseopenai": 1, "universe": 1, "opennn": 1, "orange": 1, "softwareorange": 1, "languager": 1, "spark": 1, "ml": 1, "scikitlearn": 1, "shogun": 1, "toolboxshogun": 1, "tensorflow": 2, "torch": 1, "learningtorch": 1, "weka": 1, "learningweka": 1, "yooreeka": 1, "proprietary": 2, "editions": 1, "knime": 1, "rapidminer": 1, "amazon": 1, "angoss": 1, "knowledgestudio": 1, "ayasdi": 1, "ibm": 1, "google": 2, "apisgoogle": 1, "api": 1, "spss": 2, "modeleribm": 1, "modeler": 2, "kxen": 1, "inckxen": 1, "lionsolver": 1, "mathematica": 1, "matlab": 1, "azure": 2, "studiomicrosoft": 1, "designer": 1, "neurosolutions": 1, "oracle": 1, "oraclecloudplatformasaservicepaasoracle": 1, "platform": 1, "cloud": 1, "service": 1, "rcase": 1, "sas": 1, "softwarecomponentssas": 1, "enterprise": 1, "miner": 2, "sequencel": 1, "splunk": 1, "statistica": 1, "journalneural": 1, "portalartificial": 1, "intelligencemachine": 1, "columnslist2": 1, "automatic": 1, "neuroscience": 1, "existential": 1, "risk": 1, "advanced": 1, "explanationbased": 1, "quantum": 1, "important": 1, "publications": 2, "sciencemachine": 1, "learningimportant": 1, "bioinformaticsmachinelearning": 1, "references": 1, "reflist30em": 1, "further": 1, "reading": 1, "refbegin2": 1, "nils": 1, "nilsson": 1, "httpaistanfordedupeoplenilssonmlbookhtml": 1, "trevor": 1, "robert": 1, "friedman": 1, "2001": 2, "httpswebarchiveorgweb20091110212529httpwwwstatstanfordedutibselemstatlearn": 1, "elements": 1, "springer": 1, "isbn0387952845": 1, "pedro": 1, "domingos": 1, "september": 1, "master": 1, "books": 1, "isbn9780465065707": 1, "ian": 1, "eibe": 1, "frank": 1, "morgan": 1, "kaufmann": 1, "664pp": 1, "isbn9780123748560": 1, "ethem": 1, "alpaydin": 1, "2004": 1, "isbn9780262012430": 1, "mackay": 1, "httpwwwinferencephycamacukmackayitilabookhtml": 1, "cambridge": 2, "2003": 1, "isbn0521642981": 1, "richard": 1, "o": 1, "duda": 1, "peter": 2, "hart": 1, "g": 1, "stork": 1, "2nd": 1, "edition": 1, "wiley": 1, "isbn0471056693": 1, "christopher": 1, "1995": 1, "oxford": 1, "isbn0198538642": 1, "stuart": 1, "russell": 1, "norvig": 1, "2002": 1, "prentice": 1, "hall": 1, "isbn0136042597": 1, "ray": 2, "solomonoff": 2, "ire": 1, "convention": 1, "record": 1, "section": 1, "2": 1, "5662": 1, "1957": 1, "httpworldstdcomrjsindinf56pdf": 1, "privately": 1, "circulated": 1, "1956": 1, "dartmouth": 1, "workshopdartmouth": 1, "summer": 1, "refend": 1, "external": 1, "links": 1, "httpmachinelearningorg": 1, "course": 5, "httpswwwcourseraorglearnmachinelearning": 1, "coursera": 1, "version": 1, "stanford": 1, "universitys": 1, "taught": 1, "whose": 1, "lectures": 1, "httpsseestanfordeducoursecs229": 1, "httpsmlossorg": 1, "mloss": 1, "httpsdevelopersgooglecommachinelearningcrashcourse": 1, "crash": 1, "categorymachine": 1, "categorycybernetics": 1, "categorylearning": 1}